lizard_raster_reducer/__init__.py
lizard_raster_reducer/credentials_template.yml
lizard_raster_reducer/fetching.py
lizard_raster_reducer/rasters.py
lizard_raster_reducer/reducer.py
lizard_raster_reducer/reducer_options_template.yml
lizard_raster_reducer/regions.py
lizard_raster_reducer/reporter.py
lizard_raster_reducer/scripts.py
lizard_raster_reducer/tests/__init__.py
lizard_raster_reducer/tests/test_reducer_options.yml
lizard_raster_reducer/tests/test_scripts.py
lizard_raster_reducer/tests/testdata/readme.txt
lizard_raster_reducer-0.6.dist-info/LICENSE
lizard_raster_reducer-0.6.dist-info/METADATA
lizard_raster_reducer-0.6.dist-info/WHEEL
lizard_raster_reducer-0.6.dist-info/entry_points.txt
lizard_raster_reducer-0.6.dist-info/top_level.txt
lizard_raster_reducer-0.6.dist-info/RECORD
