Metadata-Version: 2.1
Name: lizard-raster-reducer
Version: 0.6
Summary: Lizard raster reducer is a tool to auto-generate regional reports from Lizard data.
Home-page: https://github.com/nens/lizard-raster-reducer
Author: Wietze Suijker
Author-email: wietze.suijker@nelen-schuurmans.nl
License: MIT
Platform: UNKNOWN
Classifier: Programming Language :: Python
Classifier: Framework :: Django
Requires-Dist: pandas
Requires-Dist: requests
Requires-Dist: datetime
Requires-Dist: pyyaml
Provides-Extra: test
Requires-Dist: pytest ; extra == 'test'
Requires-Dist: mock ; extra == 'test'
Requires-Dist: pytest-cov ; extra == 'test'
Requires-Dist: pytest-flakes ; extra == 'test'
Requires-Dist: pytest-black ; extra == 'test'
Requires-Dist: pyyaml ; extra == 'test'
